ropgenerator/Analysis.py
ropgenerator/Colors.py
ropgenerator/Cond.py
ropgenerator/Config.py
ropgenerator/Constraints.py
ropgenerator/Database.py
ropgenerator/Expr.py
ropgenerator/Gadget.py
ropgenerator/Gadget_finder.py
ropgenerator/Graph.py
ropgenerator/Load.py
ropgenerator/Logs.py
ropgenerator/ROPGenerator.py
ropgenerator/SearchHelper.py
ropgenerator/__init__.py
ropgenerator/generate_opcodes.py
ropgenerator/test_barf.py
ropgenerator/test_single_gadget.py
ropgenerator-0.3.4.3.data/scripts/ROPGenerator
ropgenerator-0.3.4.3.dist-info/DESCRIPTION.rst
ropgenerator-0.3.4.3.dist-info/METADATA
ropgenerator-0.3.4.3.dist-info/RECORD
ropgenerator-0.3.4.3.dist-info/WHEEL
ropgenerator-0.3.4.3.dist-info/metadata.json
ropgenerator-0.3.4.3.dist-info/top_level.txt
